CHANGES.rst
MANIFEST.in
README.rst
setup.py
Flask_Bundle.egg-info/PKG-INFO
Flask_Bundle.egg-info/SOURCES.txt
Flask_Bundle.egg-info/dependency_links.txt
Flask_Bundle.egg-info/requires.txt
Flask_Bundle.egg-info/top_level.txt
flask_bundle/__init__.py
flask_bundle/api.py
flask_bundle/utils.py