Metadata-Version: 1.1
Name: Flask-Bundle
Version: 0.4
Summary: Class based tool that behaves like blueprints
Home-page: https://github.com/Deepwalker/Flask-Bundle/
Author: Svarga team, Deepwalker
Author-email: krivushinme@gmail.com
License: BSD
Download-URL: git+git://github.com/Deepwalker/Flask-Bundle.git#egg=Flask-Bundle-dev
Keywords: flask bundle
Platform: UNKNOWN
Classifier: Intended Audience :: Developers
Classifier: License :: OSI Approved :: BSD License
Classifier: Operating System :: OS Independent
Classifier: Programming Language :: Python
Classifier: Topic :: Internet :: WWW/HTTP :: Dynamic Content
Classifier: Topic :: Software Development :: Libraries :: Python Modules
